gochan/__init__.py
gochan/__main__.py
gochan/browser.py
gochan/client.py
gochan/config.py
gochan/event_handler.py
gochan/key.py
gochan/keybinding.py
gochan/parser.py
gochan/storage.py
gochan/theme.py
gochan/effects/__init__.py
gochan/effects/command_line.py
gochan/effects/help.py
gochan/effects/ng_creator.py
gochan/effects/ng_editor.py
gochan/effects/post_form.py
gochan/effects/responses_popup.py
gochan/models/__init__.py
gochan/models/app_context.py
gochan/models/bbsmenu.py
gochan/models/board.py
gochan/models/favorites.py
gochan/models/history.py
gochan/models/ng.py
gochan/models/thread.py
gochan/view_models/__init__.py
gochan/view_models/bbsmenuvm.py
gochan/view_models/boardvm.py
gochan/view_models/favoritesvm.py
gochan/view_models/imagevm.py
gochan/view_models/ngvm.py
gochan/view_models/threadvm.py
gochan/views/__init__.py
gochan/views/bbsmenu_view.py
gochan/views/board_view.py
gochan/views/favorites_view.py
gochan/views/image_view.py
gochan/views/ng_view.py
gochan/views/thread_view.py
gochan/widgets/__init__.py
gochan/widgets/list_boxk.py
gochan/widgets/multi_col_listk.py
gochan/widgets/responses_viewer.py
gochan/widgets/richtext.py
gochan-0.4.2.dist-info/AUTHORS
gochan-0.4.2.dist-info/LICENSE
gochan-0.4.2.dist-info/METADATA
gochan-0.4.2.dist-info/WHEEL
gochan-0.4.2.dist-info/entry_points.txt
gochan-0.4.2.dist-info/top_level.txt
gochan-0.4.2.dist-info/RECORD
